migreat/__init__.py
migreat/__main__.py
migreat-0.1.5.dist-info/entry_points.txt
migreat-0.1.5.dist-info/WHEEL
migreat-0.1.5.dist-info/METADATA
migreat-0.1.5.dist-info/RECORD
