Metadata-Version: 2.1
Name: migreat
Version: 0.1.5
Summary: A flexible SQL migration runner.
Home-page: https://github.com/jpmelos/migreat
License: MIT
Keywords: database,postgresql,sql,migrations
Author: João Sampaio
Author-email: jpmelos@gmail.com
Requires-Python: >=3.7,<3.10
Classifier: Development Status :: 4 - Beta
Classifier: Environment :: Console
Classifier: Intended Audience :: Developers
Classifier: Intended Audience :: System Administrators
Classifier: License :: OSI Approved :: MIT License
Classifier: Operating System :: OS Independent
Classifier: Programming Language :: Python :: 3
Classifier: Programming Language :: Python :: 3.7
Classifier: Programming Language :: Python :: 3.8
Classifier: Programming Language :: Python :: 3.9
Classifier: Topic :: Database
Requires-Dist: click (>=8,<9)
Requires-Dist: psycopg2 (>=2.8,<3)
Project-URL: Documentation, https://github.com/jpmelos/migreat
Project-URL: Repository, https://github.com/jpmelos/migreat
